FM15_bfr2geojson/__init__.py
FM15_bfr2geojson/generic_bufr2geojson.py
FM15_bfr2geojson-0.0.10.dist-info/METADATA
FM15_bfr2geojson-0.0.10.dist-info/WHEEL
FM15_bfr2geojson-0.0.10.dist-info/top_level.txt
FM15_bfr2geojson-0.0.10.dist-info/RECORD
