Metadata-Version: 2.1
Name: FM15_bfr2geojson
Version: 0.0.10
Summary: Package for converting FM15(METAR) bufr encoded messages to geojson
Author-email: Alexander Thompson <alexander.thompson@noaa.gov>
Project-URL: Homepage, https://github.com/pypa/sampleproject
Project-URL: Bug Tracker, https://github.com/pypa/sampleproject/issues
Keywords: WMO,METAR,FM-15,BUFR,decoding,weather,observations
Classifier: Development Status :: 1 - Planning
Requires-Python: >=3.7
